LICENSE
README.md
setup.py
GoogleDorker.egg-info/PKG-INFO
GoogleDorker.egg-info/SOURCES.txt
GoogleDorker.egg-info/dependency_links.txt
GoogleDorker.egg-info/entry_points.txt
GoogleDorker.egg-info/requires.txt
GoogleDorker.egg-info/top_level.txt
dorker/__init__.py
dorker/dorker.py
dorker/modules/__init__.py
dorker/modules/handler.py
dorker/modules/banner/__init__.py
dorker/modules/banner/banner.py
dorker/modules/cli/__init__.py
dorker/modules/cli/cli.py
dorker/modules/config/__init__.py
dorker/modules/config/config.py
dorker/modules/core/__init__.py
dorker/modules/core/core.py
dorker/modules/help/__init__.py
dorker/modules/help/help.py
dorker/modules/save/__init__.py
dorker/modules/save/save.py
dorker/modules/update/__init__.py
dorker/modules/update/update.py
dorker/modules/utils/__init__.py
dorker/modules/utils/utils.py
dorker/modules/version/__init__.py
dorker/modules/version/version.py