Metadata-Version: 2.1
Name: GoogleDorker
Version: 1.0.1
Summary: GoogleDorker - Unleash the power of Google dorking for ethical hackers with custom search precision.
Home-page: https://github.com/RevoltSecurities/GoogleDorker
Author: D.Sanjai Kumar
Author-email: bughunterz0047@gmail.com
License-File: LICENSE
Requires-Dist: aiofiles>=24.1.0
Requires-Dist: alive_progress>=3.2.0
Requires-Dist: appdirs>=1.4.4
Requires-Dist: art>=6.3
Requires-Dist: colorama>=0.4.4
Requires-Dist: fake_useragent>=1.5.1
Requires-Dist: httpx>=0.27.2
Requires-Dist: PyYAML>=6.0.2
Requires-Dist: Requests>=2.32.3
Requires-Dist: setuptools>=74.1.2
